.gitignore
HISTORY.md
INSTALL.md
LICENSE
README.md
setup.py
assets/DAG_CMAP.png
datgan/__init__.py
datgan/datgan.py
datgan.egg-info/PKG-INFO
datgan.egg-info/SOURCES.txt
datgan.egg-info/dependency_links.txt
datgan.egg-info/entry_points.txt
datgan.egg-info/not-zip-safe
datgan.egg-info/requires.txt
datgan.egg-info/top_level.txt
datgan/evaluation/LightGBM.py
datgan/evaluation/__init__.py
datgan/evaluation/ml_efficacy.py
datgan/evaluation/statistical_assessments.py
datgan/synthesizer/__init__.py
datgan/synthesizer/discriminator.py
datgan/synthesizer/generator.py
datgan/synthesizer/synthesizer.py
datgan/synthesizer/losses/GANLoss.py
datgan/synthesizer/losses/SGANLoss.py
datgan/synthesizer/losses/WGANLoss.py
datgan/synthesizer/losses/WGGPLoss.py
datgan/synthesizer/losses/__init__.py
datgan/utils/__init__.py
datgan/utils/dag.py
datgan/utils/data.py
datgan/utils/utils.py
example/histograms.ipynb
example/testing.ipynb
example/training.ipynb
example/data/CMAP.csv
example/data/CTABGAN.csv
example/data/CTGAN.csv
example/data/DATGAN.csv
example/data/DATGAN_ci.csv
example/data/DATGAN_ci_cond.csv
example/data/DATGAN_ci_double_cond.csv
example/data/DATGAN_cond.csv
example/data/TGAN.csv
example/data/TVAE.csv
example/encoded_data/encoded_data.pkl
example/encoded_data/continuous/age.png
example/encoded_data/continuous/departure_time.png
example/encoded_data/continuous/distance.png