Metadata-Version: 2.1
Name: datgan
Version: 2.1.9
Summary: Generative adversarial network with integrated expert knowledge for synthesizing tabular data
Home-page: https://github.com/glederrey/DATGAN
Author: Gael Lederrey
Author-email: gael.lederrey@epfl.ch
License: GPLv3
Keywords: DATGAN,GAN,Synthetic Tabular Data,Population Synthesis
Platform: UNKNOWN
Classifier: Development Status :: 3 - Alpha
Classifier: Intended Audience :: Developers
Classifier: License :: OSI Approved :: GNU General Public License v3 (GPLv3)
Classifier: Natural Language :: English
Classifier: Programming Language :: Python :: 3
Requires-Python: >=3.7
License-File: LICENSE
